databricks_mcp/__init__.py
databricks_mcp/connector.py
databricks_mcp/mcp.py
databricks_mcp/oauth_provider.py
databricks_mcp-0.5.1.dist-info/METADATA
databricks_mcp-0.5.1.dist-info/WHEEL
databricks_mcp-0.5.1.dist-info/RECORD
