Metadata-Version: 2.4
Name: databricks-mcp
Version: 0.5.1
Summary: MCP helpers for Databricks
Author-email: Databricks <agent-feedback@databricks.com>
License: Apache-2.0
Requires-Python: >=3.10
Requires-Dist: databricks-ai-bridge>=0.4.2
Requires-Dist: databricks-sdk>=0.49.0
Requires-Dist: mcp>=1.9.1
Requires-Dist: mlflow>=3.1
Provides-Extra: dev
Requires-Dist: databricks-sdk>=0.49.0; extra == 'dev'
Requires-Dist: pytest; extra == 'dev'
Requires-Dist: pytest-asyncio; extra == 'dev'
Requires-Dist: ruff==0.6.4; extra == 'dev'
Requires-Dist: typing-extensions; extra == 'dev'
Provides-Extra: integration
Requires-Dist: pytest-timeout>=2.3.1; extra == 'integration'
